{
  "unversionedId": "review/数据库部分/第18章 MySQL分区",
  "id": "review/数据库部分/第18章 MySQL分区",
  "title": "第18章 MySQL分区",
  "description": "第18章 MySQL分区",
  "source": "@site/docs/review/数据库部分/第18章 MySQL分区.md",
  "sourceDirName": "review/数据库部分",
  "slug": "/review/数据库部分/第18章 MySQL分区",
  "permalink": "/docs/review/数据库部分/第18章 MySQL分区",
  "draft": false,
  "editUrl": "https://github.com/Musicminion/2022-2023-1-Application-System-Architecture/tree/webdoc/docs/review/数据库部分/第18章 MySQL分区.md",
  "tags": [],
  "version": "current",
  "sidebarPosition": 17,
  "frontMatter": {
    "sidebar_position": 17
  },
  "sidebar": "reviewSidebar",
  "previous": {
    "title": "第17章 MySQL备份和恢复",
    "permalink": "/docs/review/数据库部分/第17章 MySQL备份和恢复"
  },
  "next": {
    "title": "第19章 MongoDB",
    "permalink": "/docs/review/数据库部分/第19章 MongoDB"
  }
}