{
  "unversionedId": "intro",
  "id": "intro",
  "title": "应用系统体系架构",
  "description": "本部分是应用系统体系架构的笔记，如果需要下载，请点击：",
  "source": "@site/docs/intro.md",
  "sourceDirName": ".",
  "slug": "/intro",
  "permalink": "/docs/intro",
  "draft": false,
  "editUrl": "https://github.com/Musicminion/2022-2023-1-Application-System-Architecture/tree/webdoc/docs/intro.md",
  "tags": [],
  "version": "current",
  "sidebarPosition": 1,
  "frontMatter": {
    "sidebar_position": 1
  },
  "sidebar": "tutorialSidebar",
  "next": {
    "title": "作业一",
    "permalink": "/docs/homework/作业一"
  }
}